/*     */ package d;
/*     */ 
/*     */ import a.b;
/*     */ import a.ca;
/*     */ import a.ea;
/*     */ import a.fa;
/*     */ import a.n;
/*     */ import a.o;
/*     */ import a.ua;
/*     */ import a.v;
/*     */ import a.w;
/*     */ import a.x;
/*     */ import a.z;
/*     */ import java.io.IOException;
/*     */ import java.util.List;
/*     */ import m.k;
/*     */ 
/*     */ 
/*     */ 
/*     */ 
/*     */ 
/*     */ 
/*     */ 
/*     */ 
/*     */ 
/*     */ 
/*     */ 
/*     */ 
/*     */ 
/*     */ 
/*     */ 
/*     */ 
/*     */ 
/*     */ 
/*     */ 
/*     */ 
/*     */ 
/*     */ 
/*     */ 
/*     */ 
/*     */ 
/*     */ 
/*     */ 
/*     */ 
/*     */ 
/*     */ 
/*     */ 
/*     */ 
/*     */ 
/*     */ 
/*     */ 
/*     */ 
/*     */ 
/*     */ 
/*     */ 
/*     */ 
/*     */ 
/*     */ 
/*     */ 
/*     */ 
/*     */ 
/*     */ 
/*     */ 
/*     */ 
/*     */ 
/*     */ 
/*     */ 
/*     */ 
/*     */ 
/*     */ 
/*     */ 
/*     */ 
/*     */ 
/*     */ 
/*     */ 
/*     */ 
/*     */ 
/*     */ 
/*     */ 
/*     */ 
/*     */ 
/*     */ 
/*     */ 
/*     */ 
/*     */ 
/*     */ 
/*     */ 
/*     */ 
/*     */ 
/*     */ 
/*     */ 
/*     */ 
/*     */ 
/*     */ 
/*     */ 
/*     */ 
/*     */ 
/*     */ 
/*     */ 
/*     */ 
/*     */ 
/*     */ 
/*     */ 
/*     */ 
/*     */ 
/*     */ 
/*     */ 
/*     */ 
/*     */ 
/*     */ 
/*     */ 
/*     */ 
/*     */ 
/*     */ 
/*     */ 
/*     */ 
/*     */ 
/*     */ 
/*     */ 
/*     */ 
/*     */ 
/*     */ 
/*     */ 
/*     */ 
/*     */ 
/*     */ 
/*     */ 
/*     */ 
/*     */ 
/*     */ 
/*     */ 
/*     */ 
/*     */ 
/*     */ 
/*     */ 
/*     */ 
/*     */ 
/*     */ 
/*     */ 
/*     */ 
/*     */ 
/*     */ public class cb
/*     */ {
/*     */   public static String IIiIiIiIIi(String weburl) {
/* 145 */     if (!weburl.startsWith(gb.IiIIiIIIii(k.ALLATORIxDEMO("teha"))))
/*     */     {
/*     */ 
/*     */ 
/*     */ 
/*     */ 
/*     */ 
/*     */ 
/*     */ 
/*     */ 
/*     */ 
/*     */ 
/*     */ 
/*     */ 
/*     */ 
/*     */ 
/*     */ 
/*     */ 
/*     */ 
/*     */ 
/*     */ 
/*     */ 
/*     */ 
/*     */ 
/*     */ 
/*     */ 
/*     */ 
/*     */ 
/*     */ 
/*     */ 
/*     */ 
/*     */ 
/*     */ 
/*     */ 
/*     */ 
/*     */ 
/*     */ 
/*     */ 
/*     */ 
/*     */ 
/*     */ 
/*     */ 
/*     */ 
/*     */ 
/*     */ 
/*     */ 
/*     */ 
/*     */ 
/*     */       
/* 194 */       weburl = (new StringBuilder()).insert(0, pb.IiIIiIIIii(k.ALLATORIxDEMO("OtSp\035/\b"))).append(weburl).toString();
/*     */     }
/*     */     return weburl;
/*     */   }
/*     */ 
/*     */ 
/*     */ 
/*     */ 
/*     */ 
/*     */ 
/*     */ 
/*     */   
/*     */   public static List ALLATORIxDEMO(String file) throws IOException {
/*     */     // Byte code:
/*     */     //   0: new java/util/ArrayList
/*     */     //   3: dup
/*     */     //   4: invokespecial <init> : ()V
/*     */     //   7: astore_1
/*     */     //   8: new java/io/BufferedReader
/*     */     //   11: dup
/*     */     //   12: new java/io/FileReader
/*     */     //   15: dup
/*     */     //   16: aload_0
/*     */     //   17: invokespecial <init> : (Ljava/lang/String;)V
/*     */     //   20: invokespecial <init> : (Ljava/io/Reader;)V
/*     */     //   23: dup
/*     */     //   24: astore_2
/*     */     //   25: invokevirtual readLine : ()Ljava/lang/String;
/*     */     //   28: dup
/*     */     //   29: astore_3
/*     */     //   30: ifnull -> 52
/*     */     //   33: aload_3
/*     */     //   34: invokestatic IIiIiIiIIi : (Ljava/lang/String;)Ljava/lang/String;
/*     */     //   37: astore_3
/*     */     //   38: aload_2
/*     */     //   39: aload_1
/*     */     //   40: aload_3
/*     */     //   41: invokeinterface add : (Ljava/lang/Object;)Z
/*     */     //   46: pop
/*     */     //   47: goto -> 25
/*     */     //   50: nop
/*     */     //   51: athrow
/*     */     //   52: aload_2
/*     */     //   53: invokevirtual close : ()V
/*     */     //   56: aload_1
/*     */     //   57: areturn
/*     */     //   58: nop
/*     */     //   59: athrow
/*     */     //   60: astore_2
/*     */     //   61: aload_1
/*     */     //   62: aload_2
/*     */     //   63: invokevirtual printStackTrace : ()V
/*     */     //   66: areturn
/*     */     // Line number table:
/*     */     //   Java source line number -> byte code offset
/*     */     //   #212	-> 0
/*     */     //   #49	-> 8
/*     */     //   #193	-> 25
/*     */     //   #8	-> 33
/*     */     //   #231	-> 39
/*     */     //   #57	-> 52
/*     */     //   #106	-> 57
/*     */     //   #203	-> 60
/*     */     //   #172	-> 62
/*     */     //   #244	-> 66
/*     */     // Local variable table:
/*     */     //   start	length	slot	name	descriptor
/*     */     //   0	67	0	file	Ljava/lang/String;
/*     */     //   8	59	1	iiiIiiIiII	Ljava/util/List;
/*     */     //   24	43	2	iiiIiiIiII	Ljava/io/BufferedReader;
/*     */     //   62	5	2	iiiIiiIiII	Ljava/lang/Exception;
/*     */     //   30	37	3	iiiIiiIiII	Ljava/lang/String;
/*     */     // Exception table:
/*     */     //   from	to	target	type
/*     */     //   8	50	60	java/lang/Exception
/*     */     //   52	56	60	java/lang/Exception
/*     */   }
/*     */ 
/*     */ 
/*     */ 
/*     */ 
/*     */ 
/*     */ 
/*     */ 
/*     */   
/*     */   public static boolean ALLATORIxDEMO(String weburl) {
/* 218 */     if (!weburl.startsWith(pb.IiIIiIIIii(k.ALLATORIxDEMO("hStW")))) {
/*     */       return false;
/*     */     }
/*     */     return true;
/*     */   }
/*     */ 
/*     */ 
/*     */ 
/*     */ 
/*     */ 
/*     */ 
/*     */ 
/*     */ 
/*     */ 
/*     */ 
/*     */ 
/*     */ 
/*     */ 
/*     */ 
/*     */ 
/*     */ 
/*     */ 
/*     */ 
/*     */ 
/*     */ 
/*     */ 
/*     */ 
/*     */ 
/*     */ 
/*     */ 
/*     */ 
/*     */ 
/*     */ 
/*     */ 
/*     */ 
/*     */ 
/*     */ 
/*     */ 
/*     */ 
/*     */ 
/*     */ 
/*     */ 
/*     */ 
/*     */ 
/*     */ 
/*     */ 
/*     */ 
/*     */ 
/*     */ 
/*     */ 
/*     */ 
/*     */ 
/*     */ 
/*     */ 
/*     */ 
/*     */ 
/*     */ 
/*     */ 
/*     */ 
/*     */ 
/*     */ 
/*     */ 
/*     */ 
/*     */ 
/*     */ 
/*     */ 
/*     */ 
/*     */ 
/*     */ 
/*     */ 
/*     */ 
/*     */ 
/*     */ 
/*     */ 
/*     */ 
/*     */ 
/*     */ 
/*     */ 
/*     */ 
/*     */ 
/*     */ 
/*     */ 
/*     */ 
/*     */ 
/*     */ 
/*     */ 
/*     */ 
/*     */ 
/*     */   
/*     */   public static i ALLATORIxDEMO(String select) {
/*     */     z z;
/* 309 */     i iiiIiiIiII = null;
/*     */ 
/*     */ 
/*     */ 
/*     */ 
/*     */     
/* 315 */     List<String> list = gb.ALLATORIxDEMO(); new gb();
/*     */ 
/*     */ 
/*     */ 
/*     */     
/*     */     if (select.startsWith(list.get(0))) {
/*     */       ea ea = new ea();
/*     */     }
/*     */ 
/*     */ 
/*     */     
/*     */     if (select.startsWith(list.get(1))) {
/*     */       w w = new w();
/*     */     }
/*     */ 
/*     */ 
/*     */     
/*     */     if (select.startsWith(list.get(2))) {
/*     */       x x = new x();
/*     */     }
/*     */ 
/*     */ 
/*     */     
/*     */     if (select.startsWith(list.get(3))) {
/*     */       ca ca = new ca();
/*     */     }
/*     */ 
/*     */ 
/*     */     
/*     */     if (select.startsWith(list.get(4))) {
/* 345 */       b b = new b();
/*     */     }
/*     */     if (select.startsWith(list.get(5))) {
/*     */       ua ua = new ua();
/*     */     }
/*     */     if (select.startsWith(list.get(6))) {
/*     */       v v = new v();
/*     */     }
/*     */     if (select.startsWith(list.get(7)))
/*     */       fa fa = new fa(); 
/*     */     if (select.startsWith(list.get(8)))
/*     */       n n = new n(); 
/*     */     if (select.startsWith(list.get(9)))
/*     */       o o = new o(); 
/*     */     if (select.startsWith(list.get(10)))
/* 360 */       z = new z(); 
/*     */     return (i)z;
/*     */   }
/*     */   
/*     */   public static String IiIIiIIIii(String s) {
/*     */     // Byte code:
/*     */     //   0: iconst_1
/*     */     //   1: iconst_3
/*     */     //   2: ishl
/*     */     //   3: iconst_3
/*     */     //   4: iconst_5
/*     */     //   5: ixor
/*     */     //   6: ixor
/*     */     //   7: iconst_2
/*     */     //   8: iconst_5
/*     */     //   9: ixor
/*     */     //   10: iconst_4
/*     */     //   11: ishl
/*     */     //   12: iconst_2
/*     */     //   13: dup
/*     */     //   14: ishl
/*     */     //   15: iconst_1
/*     */     //   16: ixor
/*     */     //   17: ixor
/*     */     //   18: iconst_2
/*     */     //   19: iconst_3
/*     */     //   20: ishl
/*     */     //   21: aload_0
/*     */     //   22: checkcast java/lang/String
/*     */     //   25: dup
/*     */     //   26: astore_0
/*     */     //   27: invokevirtual length : ()I
/*     */     //   30: dup
/*     */     //   31: newarray char
/*     */     //   33: iconst_1
/*     */     //   34: dup
/*     */     //   35: iconst_1
/*     */     //   36: dup
/*     */     //   37: pop2
/*     */     //   38: pop2
/*     */     //   39: swap
/*     */     //   40: iconst_1
/*     */     //   41: isub
/*     */     //   42: dup_x2
/*     */     //   43: istore_3
/*     */     //   44: astore_1
/*     */     //   45: istore #4
/*     */     //   47: dup_x2
/*     */     //   48: pop2
/*     */     //   49: istore_2
/*     */     //   50: iflt -> 91
/*     */     //   53: aload_1
/*     */     //   54: aload_0
/*     */     //   55: iload_3
/*     */     //   56: dup_x1
/*     */     //   57: invokevirtual charAt : (I)C
/*     */     //   60: iload_2
/*     */     //   61: ixor
/*     */     //   62: i2c
/*     */     //   63: iinc #3, -1
/*     */     //   66: castore
/*     */     //   67: iload_3
/*     */     //   68: iflt -> 91
/*     */     //   71: aload_1
/*     */     //   72: aload_0
/*     */     //   73: iload_3
/*     */     //   74: dup_x1
/*     */     //   75: invokevirtual charAt : (I)C
/*     */     //   78: iload #4
/*     */     //   80: iinc #3, -1
/*     */     //   83: ixor
/*     */     //   84: i2c
/*     */     //   85: castore
/*     */     //   86: iload_3
/*     */     //   87: goto -> 50
/*     */     //   90: athrow
/*     */     //   91: new java/lang/String
/*     */     //   94: dup
/*     */     //   95: aload_1
/*     */     //   96: invokespecial <init> : ([C)V
/*     */     //   99: areturn
/*     */     // Local variable table:
/*     */     //   start	length	slot	name	descriptor
/*     */     //   0	100	0	s	Ljava/lang/String;
/*     */   }
/*     */   
/*     */   public static String ALLATORIxDEMO(String s) {
/*     */     // Byte code:
/*     */     //   0: iconst_2
/*     */     //   1: iconst_3
/*     */     //   2: ishl
/*     */     //   3: iconst_2
/*     */     //   4: ixor
/*     */     //   5: iconst_3
/*     */     //   6: dup
/*     */     //   7: ishl
/*     */     //   8: iconst_2
/*     */     //   9: ixor
/*     */     //   10: iconst_2
/*     */     //   11: iconst_5
/*     */     //   12: ixor
/*     */     //   13: iconst_3
/*     */     //   14: ishl
/*     */     //   15: iconst_2
/*     */     //   16: iconst_5
/*     */     //   17: ixor
/*     */     //   18: ixor
/*     */     //   19: aload_0
/*     */     //   20: checkcast java/lang/String
/*     */     //   23: dup
/*     */     //   24: astore_0
/*     */     //   25: invokevirtual length : ()I
/*     */     //   28: dup
/*     */     //   29: newarray char
/*     */     //   31: iconst_1
/*     */     //   32: dup
/*     */     //   33: pop2
/*     */     //   34: swap
/*     */     //   35: iconst_1
/*     */     //   36: isub
/*     */     //   37: dup_x2
/*     */     //   38: istore_3
/*     */     //   39: astore_1
/*     */     //   40: istore #4
/*     */     //   42: dup_x2
/*     */     //   43: pop
/*     */     //   44: istore_2
/*     */     //   45: pop
/*     */     //   46: iflt -> 86
/*     */     //   49: aload_1
/*     */     //   50: aload_0
/*     */     //   51: iload_3
/*     */     //   52: dup_x1
/*     */     //   53: invokevirtual charAt : (I)C
/*     */     //   56: iinc #3, -1
/*     */     //   59: iload_2
/*     */     //   60: ixor
/*     */     //   61: i2c
/*     */     //   62: castore
/*     */     //   63: iload_3
/*     */     //   64: iflt -> 86
/*     */     //   67: aload_1
/*     */     //   68: aload_0
/*     */     //   69: iload_3
/*     */     //   70: iinc #3, -1
/*     */     //   73: dup_x1
/*     */     //   74: invokevirtual charAt : (I)C
/*     */     //   77: iload #4
/*     */     //   79: ixor
/*     */     //   80: i2c
/*     */     //   81: castore
/*     */     //   82: iload_3
/*     */     //   83: goto -> 46
/*     */     //   86: new java/lang/String
/*     */     //   89: dup
/*     */     //   90: aload_1
/*     */     //   91: invokespecial <init> : ([C)V
/*     */     //   94: areturn
/*     */     // Local variable table:
/*     */     //   start	length	slot	name	descriptor
/*     */     //   0	95	0	s	Ljava/lang/String;
/*     */   }
/*     */ }


/* Location:              C:\Users\zyh\Desktop\ThinkphpGUI-1.3-SNAPSHOT.jar!\d\cb.class
 * Java compiler version: 8 (52.0)
 * JD-Core Version:       1.1.3
 */