/*     */ package d;
/*     */ 
/*     */ import App;
/*     */ import java.util.ArrayList;
/*     */ import java.util.List;
/*     */ 
/*     */ 
/*     */ 
/*     */ 
/*     */ 
/*     */ 
/*     */ 
/*     */ 
/*     */ 
/*     */ 
/*     */ 
/*     */ 
/*     */ 
/*     */ 
/*     */ 
/*     */ 
/*     */ 
/*     */ 
/*     */ 
/*     */ 
/*     */ 
/*     */ 
/*     */ 
/*     */ 
/*     */ 
/*     */ 
/*     */ 
/*     */ 
/*     */ 
/*     */ 
/*     */ 
/*     */ 
/*     */ 
/*     */ 
/*     */ 
/*     */ 
/*     */ 
/*     */ 
/*     */ 
/*     */ 
/*     */ 
/*     */ 
/*     */ 
/*     */ 
/*     */ 
/*     */ 
/*     */ 
/*     */ 
/*     */ 
/*     */ 
/*     */ 
/*     */ 
/*     */ 
/*     */ 
/*     */ 
/*     */ 
/*     */ 
/*     */ 
/*     */ 
/*     */ 
/*     */ 
/*     */ 
/*     */ 
/*     */ 
/*     */ 
/*     */ 
/*     */ 
/*     */ public class gb
/*     */ {
/*     */   public static List ALLATORIxDEMO() {
/*     */     ArrayList<String> arrayList;
/*  77 */     arrayList.add(yb.IiIIiIIIii(App.ALLATORIxDEMO("n\020S\026Q(r(\032N\024\000\032斝忭沼霈")));
/*     */ 
/*     */ 
/*     */ 
/*     */ 
/*     */ 
/*     */ 
/*     */ 
/*     */ 
/*     */ 
/*     */ 
/*     */ 
/*     */ 
/*     */ 
/*     */ 
/*     */ 
/*     */ 
/*     */ 
/*     */ 
/*     */ 
/*     */ 
/*     */ 
/*     */ 
/*     */ 
/*     */ 
/*     */ 
/*     */ 
/*     */ 
/*     */ 
/*     */ 
/*     */ 
/*     */ 
/*     */ 
/*     */ 
/*     */ 
/*     */ 
/*     */ 
/*     */ 
/*     */ 
/*     */ 
/*     */ 
/*     */ 
/*     */ 
/*     */ 
/*     */ 
/*     */ 
/*     */ 
/*     */ 
/*     */     
/* 126 */     arrayList.add(pb.IiIIiIIIii(App.ALLATORIxDEMO("|'A!C\037`\037\b|\0067\b\003G(\b\035k\n")));
/*     */ 
/*     */ 
/*     */ 
/*     */ 
/*     */ 
/*     */ 
/*     */ 
/*     */ 
/*     */ 
/*     */ 
/*     */ 
/*     */ 
/*     */ 
/*     */ 
/*     */ 
/*     */ 
/*     */ 
/*     */ 
/*     */ 
/*     */ 
/*     */ 
/*     */ 
/*     */ 
/*     */ 
/*     */ 
/*     */ 
/*     */ 
/*     */ 
/*     */ 
/*     */ 
/*     */ 
/*     */ 
/*     */ 
/*     */ 
/*     */ 
/*     */ 
/*     */ 
/*     */ 
/*     */ 
/*     */ 
/*     */ 
/*     */ 
/*     */ 
/*     */ 
/*     */ 
/*     */ 
/*     */ 
/*     */ 
/*     */ 
/*     */ 
/*     */ 
/*     */ 
/*     */ 
/*     */ 
/*     */ 
/*     */ 
/*     */ 
/*     */ 
/*     */ 
/*     */ 
/*     */ 
/*     */ 
/*     */ 
/*     */ 
/*     */ 
/*     */ 
/*     */ 
/*     */ 
/*     */ 
/*     */ 
/*     */ 
/*     */ 
/*     */ 
/*     */ 
/*     */ 
/*     */ 
/*     */ 
/*     */ 
/*     */ 
/*     */ 
/*     */ 
/*     */ 
/*     */ 
/*     */ 
/*     */ 
/*     */ 
/*     */ 
/*     */ 
/*     */ 
/*     */ 
/*     */ 
/*     */ 
/*     */ 
/*     */ 
/*     */ 
/*     */ 
/*     */ 
/*     */ 
/*     */ 
/*     */ 
/*     */ 
/*     */ 
/*     */     
/*     */     arrayList.add(yb.IiIIiIIIii(App.ALLATORIxDEMO("n\020S\026Q(r(\032K\024\000\032斝忭沼霈")));
/*     */ 
/*     */ 
/*     */ 
/*     */ 
/*     */ 
/*     */ 
/*     */ 
/*     */ 
/*     */ 
/*     */ 
/*     */ 
/*     */ 
/*     */ 
/*     */ 
/*     */ 
/*     */ 
/*     */ 
/*     */ 
/*     */ 
/*     */ 
/*     */ 
/*     */ 
/*     */ 
/*     */ 
/*     */ 
/*     */ 
/*     */ 
/*     */ 
/*     */ 
/*     */ 
/*     */ 
/*     */ 
/*     */ 
/*     */ 
/*     */ 
/*     */ 
/*     */ 
/*     */ 
/*     */ 
/*     */ 
/*     */ 
/*     */ 
/*     */ 
/*     */ 
/*     */ 
/*     */ 
/*     */ 
/*     */ 
/*     */ 
/*     */ 
/*     */ 
/*     */ 
/*     */ 
/*     */ 
/*     */ 
/*     */ 
/*     */ 
/*     */ 
/*     */ 
/*     */ 
/*     */ 
/*     */ 
/*     */ 
/*     */ 
/*     */ 
/*     */ 
/*     */ 
/*     */ 
/*     */ 
/*     */ 
/*     */ 
/*     */ 
/*     */ 
/*     */ 
/*     */ 
/*     */ 
/*     */ 
/*     */ 
/*     */ 
/*     */ 
/*     */ 
/*     */ 
/*     */ 
/*     */ 
/*     */ 
/*     */ 
/*     */ 
/*     */ 
/*     */ 
/*     */ 
/*     */ 
/*     */ 
/*     */ 
/*     */ 
/*     */ 
/*     */ 
/*     */ 
/*     */ 
/*     */ 
/*     */ 
/*     */ 
/*     */     
/* 333 */     arrayList.add(pb.IiIIiIIIii(App.ALLATORIxDEMO("|'A!C\037`\037\b|\0067\b\035k\n")));
/*     */     arrayList.add(yb.IiIIiIIIii(App.ALLATORIxDEMO("n\020S\026Q(r(\032M\024\000\032斝忭沼霈")));
/*     */     arrayList.add(pb.IiIIiIIIii(App.ALLATORIxDEMO("|'A!C\037`\037\bz\0067\b政捆廜俉怠泬靽")));
/*     */     return arrayList.add(yb.IiIIiIIIii(App.ALLATORIxDEMO(",R\021T\023j0jX\017V\nV\bL\027M\024I\024K\nXh;")));
/*     */   }
/*     */   
/*     */   public static String ALLATORIxDEMO(String s) {
/*     */     // Byte code:
/*     */     //   0: iconst_5
/*     */     //   1: iconst_4
/*     */     //   2: ishl
/*     */     //   3: iconst_2
/*     */     //   4: iconst_1
/*     */     //   5: ishl
/*     */     //   6: ixor
/*     */     //   7: iconst_5
/*     */     //   8: iconst_4
/*     */     //   9: ishl
/*     */     //   10: iconst_2
/*     */     //   11: iconst_5
/*     */     //   12: ixor
/*     */     //   13: ixor
/*     */     //   14: iconst_2
/*     */     //   15: iconst_3
/*     */     //   16: ishl
/*     */     //   17: iconst_5
/*     */     //   18: ixor
/*     */     //   19: aload_0
/*     */     //   20: checkcast java/lang/String
/*     */     //   23: dup
/*     */     //   24: astore_0
/*     */     //   25: invokevirtual length : ()I
/*     */     //   28: dup
/*     */     //   29: newarray char
/*     */     //   31: iconst_1
/*     */     //   32: dup
/*     */     //   33: pop2
/*     */     //   34: swap
/*     */     //   35: iconst_1
/*     */     //   36: isub
/*     */     //   37: dup_x2
/*     */     //   38: istore_3
/*     */     //   39: astore_1
/*     */     //   40: istore #4
/*     */     //   42: dup_x2
/*     */     //   43: pop
/*     */     //   44: istore_2
/*     */     //   45: pop
/*     */     //   46: iflt -> 86
/*     */     //   49: aload_1
/*     */     //   50: aload_0
/*     */     //   51: iload_3
/*     */     //   52: dup_x1
/*     */     //   53: invokevirtual charAt : (I)C
/*     */     //   56: iinc #3, -1
/*     */     //   59: iload_2
/*     */     //   60: ixor
/*     */     //   61: i2c
/*     */     //   62: castore
/*     */     //   63: iload_3
/*     */     //   64: iflt -> 86
/*     */     //   67: aload_1
/*     */     //   68: aload_0
/*     */     //   69: iload_3
/*     */     //   70: iinc #3, -1
/*     */     //   73: dup_x1
/*     */     //   74: invokevirtual charAt : (I)C
/*     */     //   77: iload #4
/*     */     //   79: ixor
/*     */     //   80: i2c
/*     */     //   81: castore
/*     */     //   82: iload_3
/*     */     //   83: goto -> 46
/*     */     //   86: new java/lang/String
/*     */     //   89: dup
/*     */     //   90: aload_1
/*     */     //   91: invokespecial <init> : ([C)V
/*     */     //   94: areturn
/*     */     // Local variable table:
/*     */     //   start	length	slot	name	descriptor
/*     */     //   0	95	0	s	Ljava/lang/String;
/*     */   }
/*     */   
/*     */   public static String IiIIiIIIii(String s) {
/*     */     // Byte code:
/*     */     //   0: iconst_4
/*     */     //   1: iconst_3
/*     */     //   2: ishl
/*     */     //   3: iconst_4
/*     */     //   4: ixor
/*     */     //   5: iconst_3
/*     */     //   6: iconst_5
/*     */     //   7: ixor
/*     */     //   8: iconst_3
/*     */     //   9: ishl
/*     */     //   10: iconst_3
/*     */     //   11: iconst_5
/*     */     //   12: ixor
/*     */     //   13: ixor
/*     */     //   14: iconst_5
/*     */     //   15: aload_0
/*     */     //   16: checkcast java/lang/String
/*     */     //   19: dup
/*     */     //   20: astore_0
/*     */     //   21: invokevirtual length : ()I
/*     */     //   24: dup
/*     */     //   25: newarray char
/*     */     //   27: iconst_1
/*     */     //   28: dup
/*     */     //   29: iconst_1
/*     */     //   30: dup
/*     */     //   31: pop2
/*     */     //   32: pop2
/*     */     //   33: swap
/*     */     //   34: iconst_1
/*     */     //   35: isub
/*     */     //   36: dup_x2
/*     */     //   37: istore_3
/*     */     //   38: astore_1
/*     */     //   39: istore #4
/*     */     //   41: dup_x2
/*     */     //   42: pop2
/*     */     //   43: istore_2
/*     */     //   44: iflt -> 85
/*     */     //   47: aload_1
/*     */     //   48: aload_0
/*     */     //   49: iload_3
/*     */     //   50: dup_x1
/*     */     //   51: invokevirtual charAt : (I)C
/*     */     //   54: iload_2
/*     */     //   55: ixor
/*     */     //   56: i2c
/*     */     //   57: iinc #3, -1
/*     */     //   60: castore
/*     */     //   61: iload_3
/*     */     //   62: iflt -> 85
/*     */     //   65: aload_1
/*     */     //   66: aload_0
/*     */     //   67: iload_3
/*     */     //   68: dup_x1
/*     */     //   69: invokevirtual charAt : (I)C
/*     */     //   72: iload #4
/*     */     //   74: iinc #3, -1
/*     */     //   77: ixor
/*     */     //   78: i2c
/*     */     //   79: castore
/*     */     //   80: iload_3
/*     */     //   81: goto -> 44
/*     */     //   84: athrow
/*     */     //   85: new java/lang/String
/*     */     //   88: dup
/*     */     //   89: aload_1
/*     */     //   90: invokespecial <init> : ([C)V
/*     */     //   93: areturn
/*     */     // Local variable table:
/*     */     //   start	length	slot	name	descriptor
/*     */     //   0	94	0	s	Ljava/lang/String;
/*     */   }
/*     */ }


/* Location:              C:\Users\zyh\Desktop\ThinkphpGUI-1.3-SNAPSHOT.jar!\d\gb.class
 * Java compiler version: 8 (52.0)
 * JD-Core Version:       1.1.3
 */