/*     */ package m;
/*     */ 
/*     */ import App;
/*     */ import java.util.ArrayList;
/*     */ import java.util.List;
/*     */ 
/*     */ 
/*     */ 
/*     */ 
/*     */ 
/*     */ 
/*     */ 
/*     */ 
/*     */ 
/*     */ 
/*     */ 
/*     */ 
/*     */ 
/*     */ 
/*     */ 
/*     */ 
/*     */ 
/*     */ 
/*     */ 
/*     */ 
/*     */ 
/*     */ 
/*     */ 
/*     */ 
/*     */ 
/*     */ 
/*     */ 
/*     */ 
/*     */ 
/*     */ 
/*     */ 
/*     */ 
/*     */ 
/*     */ 
/*     */ 
/*     */ 
/*     */ 
/*     */ 
/*     */ 
/*     */ 
/*     */ 
/*     */ 
/*     */ 
/*     */ 
/*     */ 
/*     */ 
/*     */ 
/*     */ 
/*     */ 
/*     */ 
/*     */ 
/*     */ 
/*     */ 
/*     */ 
/*     */ 
/*     */ 
/*     */ 
/*     */ 
/*     */ 
/*     */ 
/*     */ 
/*     */ 
/*     */ 
/*     */ 
/*     */ 
/*     */ 
/*     */ 
/*     */ 
/*     */ 
/*     */ 
/*     */ 
/*     */ 
/*     */ 
/*     */ 
/*     */ 
/*     */ 
/*     */ 
/*     */ 
/*     */ 
/*     */ 
/*     */ 
/*     */ 
/*     */ 
/*     */ 
/*     */ 
/*     */ 
/*     */ 
/*     */ 
/*     */ 
/*     */ 
/*     */ 
/*     */ 
/*     */ 
/*     */ 
/*     */ 
/*     */ 
/*     */ 
/*     */ 
/*     */ 
/*     */ 
/*     */ 
/*     */ 
/*     */ 
/*     */ 
/*     */ 
/*     */ 
/*     */ 
/*     */ 
/*     */ 
/*     */ 
/*     */ 
/*     */ 
/*     */ 
/*     */ 
/*     */ 
/*     */ 
/*     */ 
/*     */ 
/*     */ 
/*     */ 
/*     */ 
/*     */ 
/*     */ 
/*     */ 
/*     */ 
/*     */ 
/*     */ 
/*     */ 
/*     */ 
/*     */ 
/*     */ 
/*     */ 
/*     */ 
/*     */ 
/*     */ 
/*     */ 
/*     */ 
/*     */ 
/*     */ 
/*     */ 
/*     */ 
/*     */ 
/*     */ 
/*     */ 
/*     */ 
/*     */ 
/*     */ 
/*     */ 
/*     */ 
/*     */ 
/*     */ 
/*     */ 
/*     */ 
/*     */ 
/*     */ 
/*     */ 
/*     */ 
/*     */ 
/*     */ 
/*     */ 
/*     */ 
/*     */ 
/*     */ 
/*     */ 
/*     */ 
/*     */ 
/*     */ 
/*     */ 
/*     */ 
/*     */ 
/*     */ 
/*     */ 
/*     */ 
/*     */ 
/*     */ 
/*     */ 
/*     */ 
/*     */ 
/*     */ 
/*     */ 
/*     */ 
/*     */ 
/*     */ 
/*     */ 
/*     */ 
/*     */ 
/*     */ 
/*     */ 
/*     */ 
/*     */ 
/*     */ 
/*     */ 
/*     */ 
/*     */ 
/*     */ 
/*     */ 
/*     */ 
/*     */ 
/*     */ 
/*     */ 
/*     */ 
/*     */ 
/*     */ 
/*     */ 
/*     */ 
/*     */ 
/*     */ 
/*     */ 
/*     */ 
/*     */ 
/*     */ 
/*     */ 
/*     */ 
/*     */ 
/*     */ 
/*     */ 
/*     */ 
/*     */ 
/*     */ 
/*     */ 
/*     */ 
/*     */ 
/*     */ 
/*     */ 
/*     */ 
/*     */ 
/*     */ 
/*     */ 
/*     */ 
/*     */ 
/*     */ 
/*     */ 
/*     */ 
/*     */ 
/*     */ 
/*     */ 
/*     */ 
/*     */ 
/*     */ 
/*     */ 
/*     */ 
/*     */ 
/*     */ 
/*     */ 
/*     */ 
/*     */ 
/*     */ 
/*     */ 
/*     */ 
/*     */ 
/*     */ 
/*     */ 
/*     */ 
/*     */ 
/*     */ 
/*     */ 
/*     */ 
/*     */ 
/*     */ 
/*     */ 
/*     */ 
/*     */ 
/*     */ 
/*     */ 
/*     */ 
/*     */ 
/*     */ 
/*     */ 
/*     */ 
/*     */ 
/*     */ 
/*     */ 
/*     */ 
/*     */ 
/*     */ 
/*     */ 
/*     */ 
/*     */ 
/*     */ 
/*     */ 
/*     */ 
/*     */ 
/*     */ 
/*     */ 
/*     */ 
/*     */ 
/*     */ 
/*     */ 
/*     */ 
/*     */ 
/*     */ 
/*     */ 
/*     */ 
/*     */ 
/*     */ 
/*     */ 
/*     */ 
/*     */ 
/*     */ 
/*     */ 
/*     */ 
/*     */ 
/*     */ 
/*     */ 
/*     */ 
/*     */ 
/*     */ 
/*     */ 
/*     */ 
/*     */ public class d
/*     */ {
/*     */   public static String ALLATORIxDEMO(String s) {
/*     */     // Byte code:
/*     */     //   0: iconst_1
/*     */     //   1: iconst_3
/*     */     //   2: ishl
/*     */     //   3: iconst_2
/*     */     //   4: iconst_5
/*     */     //   5: ixor
/*     */     //   6: ixor
/*     */     //   7: iconst_5
/*     */     //   8: iconst_4
/*     */     //   9: ishl
/*     */     //   10: iconst_3
/*     */     //   11: iconst_5
/*     */     //   12: ixor
/*     */     //   13: iconst_1
/*     */     //   14: ishl
/*     */     //   15: ixor
/*     */     //   16: iconst_3
/*     */     //   17: dup
/*     */     //   18: ishl
/*     */     //   19: iconst_5
/*     */     //   20: ixor
/*     */     //   21: aload_0
/*     */     //   22: checkcast java/lang/String
/*     */     //   25: dup
/*     */     //   26: astore_0
/*     */     //   27: invokevirtual length : ()I
/*     */     //   30: dup
/*     */     //   31: newarray char
/*     */     //   33: iconst_1
/*     */     //   34: dup
/*     */     //   35: pop2
/*     */     //   36: swap
/*     */     //   37: iconst_1
/*     */     //   38: isub
/*     */     //   39: dup_x2
/*     */     //   40: istore_3
/*     */     //   41: astore_1
/*     */     //   42: istore #4
/*     */     //   44: dup_x2
/*     */     //   45: pop
/*     */     //   46: istore_2
/*     */     //   47: pop
/*     */     //   48: iflt -> 88
/*     */     //   51: aload_1
/*     */     //   52: aload_0
/*     */     //   53: iload_3
/*     */     //   54: dup_x1
/*     */     //   55: invokevirtual charAt : (I)C
/*     */     //   58: iinc #3, -1
/*     */     //   61: iload_2
/*     */     //   62: ixor
/*     */     //   63: i2c
/*     */     //   64: castore
/*     */     //   65: iload_3
/*     */     //   66: iflt -> 88
/*     */     //   69: aload_1
/*     */     //   70: aload_0
/*     */     //   71: iload_3
/*     */     //   72: iinc #3, -1
/*     */     //   75: dup_x1
/*     */     //   76: invokevirtual charAt : (I)C
/*     */     //   79: iload #4
/*     */     //   81: ixor
/*     */     //   82: i2c
/*     */     //   83: castore
/*     */     //   84: iload_3
/*     */     //   85: goto -> 48
/*     */     //   88: new java/lang/String
/*     */     //   91: dup
/*     */     //   92: aload_1
/*     */     //   93: invokespecial <init> : ([C)V
/*     */     //   96: areturn
/*     */     // Local variable table:
/*     */     //   start	length	slot	name	descriptor
/*     */     //   0	97	0	s	Ljava/lang/String;
/*     */   }
/*     */   
/*     */   public static List ALLATORIxDEMO() {
/*     */     ArrayList<String> arrayList;
/* 323 */     arrayList.add(j.ALLATORIxDEMO(";{\006}\004C'CO%AkO时徸泗靝"));
/*     */     arrayList.add(App.ALLATORIxDEMO("e5X3Z\ry\r\021n\037%\021\021^:\021\017r\030"));
/*     */     arrayList.add(j.ALLATORIxDEMO(";{\006}\004C'CO AkO时徸泗靝"));
/*     */     arrayList.add(App.ALLATORIxDEMO("e5X3Z\ry\r\021n\037%\021\017r\030"));
/*     */     arrayList.add(j.ALLATORIxDEMO(";{\006}\004C'CO&AkO时徸泗靝"));
/*     */     arrayList.add(App.ALLATORIxDEMO("e5X3Z\ry\r\021h\037%\021攭损廎俐怲泵靯"));
/*     */     return arrayList.add(j.ALLATORIxDEMO("G\007z\001x?[?3Z=_=]'B&A\"A _3=P*"));
/*     */   }
/*     */ }


/* Location:              C:\Users\zyh\Desktop\ThinkphpGUI-1.3-SNAPSHOT.jar!\m\d.class
 * Java compiler version: 8 (52.0)
 * JD-Core Version:       1.1.3
 */