/*     */ package m;
/*     */ 
/*     */ import d.yb;
/*     */ import java.io.BufferedReader;
/*     */ import java.io.FileReader;
/*     */ import java.io.IOException;
/*     */ import java.util.ArrayList;
/*     */ import java.util.List;
/*     */ import p.aa;
/*     */ import p.db;
/*     */ import p.fb;
/*     */ import p.ga;
/*     */ import p.hb;
/*     */ import p.ja;
/*     */ import p.jb;
/*     */ import p.ka;
/*     */ import p.kb;
/*     */ import p.ta;
/*     */ import p.xa;
/*     */ 
/*     */ 
/*     */ 
/*     */ 
/*     */ 
/*     */ 
/*     */ 
/*     */ 
/*     */ 
/*     */ 
/*     */ 
/*     */ 
/*     */ 
/*     */ 
/*     */ 
/*     */ 
/*     */ 
/*     */ 
/*     */ 
/*     */ 
/*     */ 
/*     */ 
/*     */ 
/*     */ 
/*     */ 
/*     */ 
/*     */ 
/*     */ 
/*     */ 
/*     */ 
/*     */ 
/*     */ 
/*     */ 
/*     */ 
/*     */ 
/*     */ 
/*     */ 
/*     */ 
/*     */ 
/*     */ 
/*     */ 
/*     */ 
/*     */ 
/*     */ 
/*     */ 
/*     */ 
/*     */ 
/*     */ 
/*     */ 
/*     */ 
/*     */ 
/*     */ 
/*     */ 
/*     */ 
/*     */ 
/*     */ 
/*     */ 
/*     */ 
/*     */ 
/*     */ 
/*     */ 
/*     */ 
/*     */ 
/*     */ 
/*     */ 
/*     */ 
/*     */ 
/*     */ 
/*     */ 
/*     */ 
/*     */ 
/*     */ 
/*     */ 
/*     */ 
/*     */ 
/*     */ 
/*     */ 
/*     */ 
/*     */ 
/*     */ 
/*     */ 
/*     */ 
/*     */ 
/*     */ 
/*     */ 
/*     */ 
/*     */ 
/*     */ 
/*     */ 
/*     */ 
/*     */ 
/*     */ 
/*     */ 
/*     */ 
/*     */ 
/*     */ 
/*     */ 
/*     */ 
/*     */ 
/*     */ 
/*     */ 
/*     */ 
/*     */ 
/*     */ 
/*     */ 
/*     */ 
/*     */ 
/*     */ 
/*     */ 
/*     */ 
/*     */ 
/*     */ 
/*     */ 
/*     */ 
/*     */ 
/*     */ 
/*     */ 
/*     */ 
/*     */ 
/*     */ 
/*     */ 
/*     */ 
/*     */ 
/*     */ 
/*     */ 
/*     */ 
/*     */ 
/*     */ 
/*     */ 
/*     */ 
/*     */ 
/*     */ 
/*     */ 
/*     */ 
/*     */ 
/*     */ 
/*     */ 
/*     */ 
/*     */ 
/*     */ 
/*     */ public class k
/*     */ {
/*     */   public static String ALLATORIxDEMO(String s) {
/*     */     // Byte code:
/*     */     //   0: iconst_3
/*     */     //   1: iconst_5
/*     */     //   2: ixor
/*     */     //   3: iconst_4
/*     */     //   4: ishl
/*     */     //   5: iconst_3
/*     */     //   6: iconst_2
/*     */     //   7: ishl
/*     */     //   8: iconst_3
/*     */     //   9: ixor
/*     */     //   10: ixor
/*     */     //   11: iconst_3
/*     */     //   12: iconst_5
/*     */     //   13: ixor
/*     */     //   14: iconst_3
/*     */     //   15: ishl
/*     */     //   16: iconst_5
/*     */     //   17: ixor
/*     */     //   18: iconst_3
/*     */     //   19: dup
/*     */     //   20: ishl
/*     */     //   21: iconst_1
/*     */     //   22: ixor
/*     */     //   23: aload_0
/*     */     //   24: checkcast java/lang/String
/*     */     //   27: dup
/*     */     //   28: astore_0
/*     */     //   29: invokevirtual length : ()I
/*     */     //   32: dup
/*     */     //   33: newarray char
/*     */     //   35: iconst_1
/*     */     //   36: dup
/*     */     //   37: pop2
/*     */     //   38: swap
/*     */     //   39: iconst_1
/*     */     //   40: isub
/*     */     //   41: dup_x2
/*     */     //   42: istore_3
/*     */     //   43: astore_1
/*     */     //   44: istore #4
/*     */     //   46: dup_x2
/*     */     //   47: pop
/*     */     //   48: istore_2
/*     */     //   49: pop
/*     */     //   50: iflt -> 90
/*     */     //   53: aload_1
/*     */     //   54: aload_0
/*     */     //   55: iload_3
/*     */     //   56: dup_x1
/*     */     //   57: invokevirtual charAt : (I)C
/*     */     //   60: iinc #3, -1
/*     */     //   63: iload_2
/*     */     //   64: ixor
/*     */     //   65: i2c
/*     */     //   66: castore
/*     */     //   67: iload_3
/*     */     //   68: iflt -> 90
/*     */     //   71: aload_1
/*     */     //   72: aload_0
/*     */     //   73: iload_3
/*     */     //   74: iinc #3, -1
/*     */     //   77: dup_x1
/*     */     //   78: invokevirtual charAt : (I)C
/*     */     //   81: iload #4
/*     */     //   83: ixor
/*     */     //   84: i2c
/*     */     //   85: castore
/*     */     //   86: iload_3
/*     */     //   87: goto -> 50
/*     */     //   90: new java/lang/String
/*     */     //   93: dup
/*     */     //   94: aload_1
/*     */     //   95: invokespecial <init> : ([C)V
/*     */     //   98: areturn
/*     */     // Local variable table:
/*     */     //   start	length	slot	name	descriptor
/*     */     //   0	99	0	s	Ljava/lang/String;
/*     */   }
/*     */   
/*     */   public static String IiIIiIIIii(String weburl) {
/* 167 */     if (!weburl.startsWith(yb.ALLATORIxDEMO("BE^A")))
/*     */     {
/*     */ 
/*     */ 
/*     */ 
/*     */ 
/*     */ 
/*     */ 
/*     */ 
/*     */ 
/*     */ 
/*     */ 
/*     */ 
/*     */ 
/*     */ 
/*     */ 
/*     */ 
/*     */ 
/*     */ 
/*     */ 
/*     */ 
/*     */ 
/*     */ 
/*     */ 
/*     */ 
/*     */ 
/*     */ 
/*     */ 
/*     */ 
/*     */ 
/*     */ 
/*     */ 
/*     */ 
/*     */ 
/*     */ 
/*     */ 
/*     */ 
/*     */ 
/*     */ 
/*     */ 
/*     */ 
/*     */ 
/*     */ 
/*     */ 
/*     */ 
/*     */ 
/*     */ 
/*     */ 
/*     */ 
/*     */ 
/*     */ 
/*     */ 
/*     */ 
/*     */ 
/*     */ 
/*     */ 
/*     */ 
/*     */ 
/*     */ 
/*     */ 
/*     */ 
/*     */ 
/*     */ 
/*     */ 
/*     */ 
/*     */ 
/*     */ 
/*     */ 
/*     */ 
/*     */ 
/*     */ 
/*     */ 
/*     */ 
/*     */ 
/*     */ 
/*     */ 
/*     */ 
/*     */ 
/*     */ 
/*     */ 
/*     */ 
/*     */ 
/*     */ 
/*     */ 
/*     */ 
/*     */ 
/*     */ 
/*     */ 
/*     */ 
/*     */ 
/*     */ 
/*     */ 
/*     */ 
/*     */ 
/*     */ 
/*     */ 
/*     */ 
/*     */ 
/*     */ 
/*     */ 
/*     */ 
/*     */ 
/*     */ 
/*     */ 
/*     */ 
/*     */ 
/*     */ 
/*     */ 
/*     */ 
/*     */ 
/*     */ 
/*     */ 
/*     */ 
/*     */ 
/*     */ 
/*     */ 
/*     */ 
/*     */ 
/*     */ 
/*     */ 
/*     */ 
/*     */ 
/*     */ 
/*     */ 
/*     */ 
/*     */ 
/*     */ 
/*     */ 
/*     */ 
/*     */ 
/*     */ 
/*     */ 
/*     */ 
/*     */ 
/*     */ 
/*     */ 
/*     */ 
/*     */ 
/*     */ 
/*     */ 
/*     */ 
/*     */ 
/*     */ 
/*     */ 
/*     */ 
/*     */ 
/*     */ 
/*     */ 
/*     */ 
/*     */ 
/*     */ 
/*     */ 
/*     */ 
/*     */ 
/*     */ 
/*     */ 
/*     */ 
/*     */ 
/*     */ 
/*     */ 
/*     */ 
/*     */ 
/*     */ 
/*     */ 
/*     */ 
/*     */ 
/*     */       
/* 334 */       weburl = (new StringBuilder()).insert(0, ALLATORIxDEMO("]mAi\0176\032")).append(weburl).toString(); }  return weburl; } public static c ALLATORIxDEMO(String select) { xa xa; c iiiIiiIiII = null; List<String> list = d.ALLATORIxDEMO(); new d(); if (select.startsWith(list.get(0)))
/*     */       db db = new db();  if (select.startsWith(list.get(1)))
/*     */       fb fb = new fb();  if (select.startsWith(list.get(2)))
/*     */       ga ga = new ga();  if (select.startsWith(list.get(3)))
/*     */       ja ja = new ja(); 
/*     */     if (select.startsWith(list.get(4)))
/*     */       aa aa = new aa(); 
/*     */     if (select.startsWith(list.get(5)))
/*     */       ka ka = new ka(); 
/*     */     if (select.startsWith(list.get(6)))
/*     */       ta ta = new ta(); 
/* 345 */     if (select.startsWith(list.get(7)))
/*     */       jb jb = new jb();  if (select.startsWith(list.get(8)))
/*     */       kb kb = new kb();  if (select.startsWith(list.get(9)))
/*     */       hb hb = new hb();  if (select.startsWith(list.get(10)))
/*     */       xa = new xa();  return (c)xa; } public static boolean ALLATORIxDEMO(String weburl) { if (!weburl.startsWith(ALLATORIxDEMO("qAmE")))
/*     */       return false;  return true; }
/*     */   public static List ALLATORIxDEMO(String file) throws IOException { List<String> iiiIiiIiII = new ArrayList();
/*     */     try {
/*     */       BufferedReader bufferedReader;
/*     */       while (true) {
/*     */         String str;
/*     */         if ((str = (bufferedReader = new BufferedReader(new FileReader(file))).readLine()) != null) {
/* 357 */           str = IiIIiIIIii(str);
/*     */           iiiIiiIiII.add(str);
/*     */           continue;
/*     */         } 
/*     */         bufferedReader.close();
/*     */         return iiiIiiIiII;
/*     */       } 
/*     */     } catch (Exception exception) {
/*     */       exception.printStackTrace();
/*     */       return iiiIiiIiII;
/*     */     }  }
/*     */ 
/*     */ }


/* Location:              C:\Users\zyh\Desktop\ThinkphpGUI-1.3-SNAPSHOT.jar!\m\k.class
 * Java compiler version: 8 (52.0)
 * JD-Core Version:       1.1.3
 */